fintself/__init__.py
fintself/cli.py
fintself/settings.py
fintself/core/exceptions.py
fintself/core/models.py
fintself/scrapers/__init__.py
fintself/scrapers/base.py
fintself/scrapers/cl/__init__.py
fintself/scrapers/cl/banco_chile.py
fintself/scrapers/cl/cencosud.py
fintself/scrapers/cl/santander.py
fintself/utils/__init__.py
fintself/utils/logging.py
fintself/utils/output.py
fintself/utils/parsers.py
fintself-1.1.0.dist-info/licenses/LICENSE
fintself-1.1.0.dist-info/METADATA
fintself-1.1.0.dist-info/WHEEL
fintself-1.1.0.dist-info/entry_points.txt
fintself-1.1.0.dist-info/top_level.txt
fintself-1.1.0.dist-info/RECORD
