Metadata-Version: 2.4
Name: fintself
Version: 1.1.0
Summary: Open source collaborative bank transaction scraper for Chilean banks.
Requires-Python: >=3.9
License-File: LICENSE
Requires-Dist: loguru>=0.7.3
Requires-Dist: openpyxl>=3.1.5
Requires-Dist: pandas>=2.3.1
Requires-Dist: python-dotenv>=1.1.1
Requires-Dist: playwright>=1.42.0
Requires-Dist: pydantic>=2.11.7
Requires-Dist: typer>=0.16.0
Provides-Extra: dev
Requires-Dist: pytest>=8.4.1; extra == "dev"
Requires-Dist: pytest-mock>=3.14.1; extra == "dev"
Requires-Dist: ipykernel>=6.30.0; extra == "dev"
Requires-Dist: ipywidgets>=8.1.7; extra == "dev"
Dynamic: license-file
